django_rest_framework_recursive/__init__.py
django_rest_framework_recursive/fields.py
django_rest_framework_recursive/py.typed
drf_recursive-0.4.0.dist-info/LICENSE
drf_recursive-0.4.0.dist-info/METADATA
drf_recursive-0.4.0.dist-info/WHEEL
drf_recursive-0.4.0.dist-info/top_level.txt
drf_recursive-0.4.0.dist-info/RECORD
