Metadata-Version: 2.1
Name: drf-recursive
Version: 0.4.0
Project-URL: repository, https://github.com/kraken-tech/django-rest-framework-recursive
Project-URL: changelog, https://github.com/kraken-tech/django-rest-framework-recursive/blob/master/CHANGELOG.md
License-File: LICENSE
Requires-Dist: django >=3.2
Requires-Dist: djangorestframework >=3.12.0
Provides-Extra: dev
Requires-Dist: pytest ; extra == 'dev'
Requires-Dist: pytest-django >=4.7.0 ; extra == 'dev'
Requires-Dist: pytest-cov ; extra == 'dev'
Requires-Dist: nox ; extra == 'dev'
Requires-Dist: ruff ; extra == 'dev'
Requires-Dist: mypy ; extra == 'dev'
Requires-Dist: build ; extra == 'dev'
Requires-Dist: bump-my-version ; extra == 'dev'
